Workbook

Sheet Menú Principal
C4: Factura 2022 Club de Baloncesto Moratalaz
C6: Páginas de la Factura
C7: Estadísticas
C8: Gancias y Gastos
C9: Salarios
C10: Balance Total

Sheet Estadísticas
B1: Gastos de campaña
B2: Concepto | C2: Total | D2: Media
B3: =' Gancias y Gastos'!B25 -> Almacenamiento | C3: =SUM(' Gancias y Gastos'!C25:H25) -> 3546789.1 | D3: =AVERAGE(' Gancias y Gastos'!C25:H25) -> 591131.52 | K3: Tipo de personal | L3: Salario Anual
B4: =' Gancias y Gastos'!B26 -> Producción equipaciones de juego | C4: =SUM(' Gancias y Gastos'!C26:H26) -> 206237.74 | D4: =AVERAGE(' Gancias y Gastos'!C26:H26) -> 34372.957 | K4: Cuerpo Técnico | L4: 851657.14
B5: =' Gancias y Gastos'!B27 -> Empresa tiendas físicas y online | C5: =SUM(' Gancias y Gastos'!C27:H27) -> 5010000 | D5: =AVERAGE(' Gancias y Gastos'!C27:H27) -> 835000 | K5: Directiva | L5: 5184000
B6: =' Gancias y Gastos'!B28 -> Empresa limpieza campos | C6: =SUM(' Gancias y Gastos'!C28:H28) -> 435000 | D6: =AVERAGE(' Gancias y Gastos'!C28:H28) -> 72500 | K6: Logística | L6: 2530285.7
B7: =' Gancias y Gastos'!B29 -> Empresa Mantenimiento de Campo | C7: =SUM(' Gancias y Gastos'!C29:H29) -> 1550000 | D7: =AVERAGE(' Gancias y Gastos'!C29:H29) -> 258333.33 | K7: Plantilla | L7: 4640914.3
B8: =' Gancias y Gastos'!B30 -> Materiales de entrenamiento especializados | C8: =SUM(' Gancias y Gastos'!C30:H30) -> 1213036.4 | D8: =AVERAGE(' Gancias y Gastos'!C30:H30) -> 202172.73 | K8: Total general | L8: 13206857
B9: =' Gancias y Gastos'!B31 -> Hoteles | C9: =SUM(' Gancias y Gastos'!C31:H31) -> 1493005 | D9: =AVERAGE(' Gancias y Gastos'!C31:H31) -> 248834.17
B10: =' Gancias y Gastos'!B32 -> Viajes | C10: =SUM(' Gancias y Gastos'!C32:H32) -> 325701 | D10: =AVERAGE(' Gancias y Gastos'!C32:H32) -> 54283.5
B11: =' Gancias y Gastos'!B33 -> Dietas | C11: =SUM(' Gancias y Gastos'!C33:H33) -> 1419719 | D11: =AVERAGE(' Gancias y Gastos'!C33:H33) -> 236619.83
B12: =' Gancias y Gastos'!B34 -> Fichajes | C12: =SUM(' Gancias y Gastos'!C34:H34) -> 5690000 | D12: =AVERAGE(' Gancias y Gastos'!C34:H34) -> 948333.33
B13: =' Gancias y Gastos'!B35 -> Anuncios del club | C13: =SUM(' Gancias y Gastos'!C35:H35) -> 1299000 | D13: =AVERAGE(' Gancias y Gastos'!C35:H35) -> 216500
B14: =' Gancias y Gastos'!B36 -> Servidores web | C14: =SUM(' Gancias y Gastos'!C36:H36) -> 562000 | D14: =AVERAGE(' Gancias y Gastos'!C36:H36) -> 93666.667
B15: =' Gancias y Gastos'!B37 -> Marketing redes sociales | C15: =SUM(' Gancias y Gastos'!C37:H37) -> 1117911 | D15: =AVERAGE(' Gancias y Gastos'!C37:H37) -> 186318.5
B16: =' Gancias y Gastos'!B38 -> Producción productos de merchandishing | C16: =SUM(' Gancias y Gastos'!C38:H38) -> 1345786 | D16: =AVERAGE(' Gancias y Gastos'!C38:H38) -> 224297.67

Sheet  Gancias y Gastos
B3: Ingresos y gastos
B6: INGRESOS
B11: Concepto | C11: Ingresos | D11: Ingresos netos
B12: Liga Endesa | C12: 10500000 | D12: =Tabla11[[#This Row],[Ingresos]]-(Tabla11[[#This Row],[Ingresos]]*0.2) -> 8400000 | F12: Ingreso Máximo | G12: =MAX(Tabla11[[Ingresos]:[Ingresos netos]]) -> 80000000
B13: Euroliga | C13: 3400000 | D13: =Tabla11[[#This Row],[Ingresos]]-(Tabla11[[#This Row],[Ingresos]]*0.2) -> 2720000
B14: Venta de productos de merchandishing | C14: 35648964 | D14: =Tabla11[[#This Row],[Ingresos]]-(Tabla11[[#This Row],[Ingresos]]*0.2) -> 28519172 | F14: Ingreso Mínimo | G14: =MIN(Tabla11[[Ingresos]:[Ingresos netos]]) -> 106400
B15: Venta de entradas | C15: 3672896 | D15: =Tabla11[[#This Row],[Ingresos]]-(Tabla11[[#This Row],[Ingresos]]*0.2) -> 2938316.8
B16: Copa del Rey | C16: 4100000 | D16: =Tabla11[[#This Row],[Ingresos]]-(Tabla11[[#This Row],[Ingresos]]*0.2) -> 3280000 | F16: Ingreso Medio | G16: =AVERAGE(Tabla11[[Ingresos]:[Ingresos netos]]) -> 12754837
B17: Donaciones | C17: 567893 | D17: =Tabla11[[#This Row],[Ingresos]]-(Tabla11[[#This Row],[Ingresos]]*0.2) -> 454314.4
B18: Sponsors (Iphone) | C18: 80000000 | D18: =Tabla11[[#This Row],[Ingresos]]-(Tabla11[[#This Row],[Ingresos]]*0.2) -> 64000000
B19: Prima por primera división | C19: 133000 | D19: =Tabla11[[#This Row],[Ingresos]]-(Tabla11[[#This Row],[Ingresos]]*0.2) -> 106400
B20: Derechos de imagen | C20: 876342 | D20: =Tabla11[[#This Row],[Ingresos]]-(Tabla11[[#This Row],[Ingresos]]*0.2) -> 701073.6
B21: Anuncios página web | C21: 2821312 | D21: =Tabla11[[#This Row],[Ingresos]]-(Tabla11[[#This Row],[Ingresos]]*0.2) -> 2257049.6
B23: GASTOS
B24: Concepto | C24: Liga Endesa | D24: Euroliga | E24: Venta de productos de merchandishing | F24: Venta de entradas | G24: Copa del Rey | H24: Anuncios página web
B25: Almacenamiento | C25: 0 | D25: 0 | E25: 3546789.1 | F25: 0 | G25: 0 | H25: 0
B26: Producción equipaciones de juego | C26: 194556.86 | D26: 7891.55 | E26: 0 | F26: 0 | G26: 3789.33 | H26: 0
B27: Empresa tiendas físicas y online | C27: 0 | D27: 0 | E27: 2500000 | F27: 2500000 | G27: 0 | H27: 10000
B28: Empresa limpieza campos | C28: 400000 | D28: 20000 | E28: 0 | F28: 0 | G28: 15000 | H28: 0
B29: Empresa Mantenimiento de Campo | C29: 1000000 | D29: 300000 | E29: 0 | F29: 0 | G29: 250000 | H29: 0
B30: Materiales de entrenamiento especializados | C30: 573678.84 | D30: 85789.78 | E30: 0 | F30: 0 | G30: 553567.76 | H30: 0
B31: Hoteles | C31: 826876 | D31: 150456 | E31: 0 | F31: 0 | G31: 515673 | H31: 0
B32: Viajes | C32: 147893 | D32: 88456 | E32: 0 | F32: 0 | G32: 89352 | H32: 0
B33: Dietas | C33: 578245.99 | D33: 425793.99 | E33: 0 | F33: 0 | G33: 415678.99 | H33: 0
B34: Fichajes | C34: 2350000 | D34: 1120000 | E34: 0 | F34: 0 | G34: 2220000 | H34: 0
B35: Anuncios del club | C35: 335000 | D35: 450000 | E35: 150000 | F35: 234000 | G35: 130000 | H35: 0
B36: Servidores web | C36: 0 | D36: 0 | E36: 15000 | F36: 10000 | G36: 0 | H36: 537000
... B38: Producción productos de merchandishing | C38: 0 | D38: 0 | E38: 1345786 | F38: 0 | G38: 0 | H38: 0
B39: TOTAL | C39: =SUBTOTAL(109,C25:C38) -> 6422705.7 | D39: =SUBTOTAL(109,D25:D38) -> 2674126.3 | E39: =SUBTOTAL(109,E25:E38) -> 7592393.1 | F39: =SUBTOTAL(109,F25:F38) -> 2775987 | G39: =SUBTOTAL(109,G25:G38) -> 4201973.1 | H39: =SUBTOTAL(109,H25:H38) -> 1547000
B41: Gasto máximo por concepto | C41: =SUBTOTAL(104,Tabla5[Liga Endesa]) -> 2350000 | D41: =SUBTOTAL(104,Tabla5[Euroliga]) -> 1120000 | E41: =SUBTOTAL(104,Tabla5[Venta de productos de merchandishing]) -> 3546789.1 | F41: =SUBTOTAL(104,Tabla5[Venta de entradas]) -> 2500000 | G41: =SUBTOTAL(104,Tabla5[Copa del Rey]) -> 2220000 | H41: =SUBTOTAL(104,Tabla5[Anuncios página web]) -> 1000000

Sheet Salarios
A3: Tipo de Personal | B3: Rango | C3: Nombre | D3: Apellidos | E3: Salario/mes | F3: Salario Total | G3: Prima por Contrato | H3: Total del Año
A4: Directiva | B4: Presidente | C4: Odey | D4: Muñoz Cruz | E4: 190000 | F4: =Tabla54[[#This Row],[Salario/mes]]*12 -> 2280000 | G4: =(Tabla54[[#This Row],[Salario Total]]/7)/5 -> 65142.857 | H4: =Tabla54[[#This Row],[Salario Total]]+Tabla54[[#This Row],[Prima por Contrato]] -> 2345142.9
A5: Directiva | B5: Secretario General | C5: Razvan Adríán Vasile | D5: Borz | E5: 80000 | F5: =Tabla54[[#This Row],[Salario/mes]]*12 -> 960000 | G5: =(Tabla54[[#This Row],[Salario Total]]/7)/5 -> 27428.571 | H5: =Tabla54[[#This Row],[Salario Total]]+Tabla54[[#This Row],[Prima por Contrato]] -> 987428.57
A6: Directiva | B6: Delegado de Campo | C6: Alejandro | D6: Portillo Díaz | E6: 150000 | F6: =Tabla54[[#This Row],[Salario/mes]]*12 -> 1800000 | G6: =(Tabla54[[#This Row],[Salario Total]]/7)/5 -> 51428.571 | H6: =Tabla54[[#This Row],[Salario Total]]+Tabla54[[#This Row],[Prima por Contrato]] -> 1851428.6
A7: Cuerpo Técnico | B7: Entrenador | C7: José Manuel | D7: Díaz Fernandez | E7: 44000 | F7: =Tabla54[[#This Row],[Salario/mes]]*12 -> 528000 | G7: =(Tabla54[[#This Row],[Salario Total]]/7)/5 -> 15085.714 | H7: =Tabla54[[#This Row],[Salario Total]]+Tabla54[[#This Row],[Prima por Contrato]] -> 543085.71
A8: Cuerpo Técnico | B8: Segundo Entrenador | C8: Diego Pablo | D8: Simeone | E8: 25000 | F8: =Tabla54[[#This Row],[Salario/mes]]*12 -> 300000 | G8: =(Tabla54[[#This Row],[Salario Total]]/7)/5 -> 8571.4286 | H8: =Tabla54[[#This Row],[Salario Total]]+Tabla54[[#This Row],[Prima por Contrato]] -> 308571.43
A9: Plantilla | B9: Jugador | C9: Mario | D9: Montalvo Palacios | E9: 100500 | F9: =Tabla54[[#This Row],[Salario/mes]]*12 -> 1206000 | G9: =(Tabla54[[#This Row],[Salario Total]]/7)/5 -> 34457.143 | H9: =Tabla54[[#This Row],[Salario Total]]+Tabla54[[#This Row],[Prima por Contrato]] -> 1240457.1
A10: Plantilla | B10: Jugador | C10: Jesús | D10: Nieto Rodríguez | E10: 80000 | F10: =Tabla54[[#This Row],[Salario/mes]]*12 -> 960000 | G10: =(Tabla54[[#This Row],[Salario Total]]/7)/5 -> 27428.571 | H10: =Tabla54[[#This Row],[Salario Total]]+Tabla54[[#This Row],[Prima por Contrato]] -> 987428.57
A11: Plantilla | B11: Jugador | C11: Koldo | D11: De Diego | E11: 24000 | F11: =Tabla54[[#This Row],[Salario/mes]]*12 -> 288000 | G11: =(Tabla54[[#This Row],[Salario Total]]/7)/5 -> 8228.5714 | H11: =Tabla54[[#This Row],[Salario Total]]+Tabla54[[#This Row],[Prima por Contrato]] -> 296228.57
A12: Plantilla | B12: Jugador | C12: Hugo | D12: Moreno Sabater | E12: 15000 | F12: =Tabla54[[#This Row],[Salario/mes]]*12 -> 180000 | G12: =(Tabla54[[#This Row],[Salario Total]]/7)/5 -> 5142.8571 | H12: =Tabla54[[#This Row],[Salario Total]]+Tabla54[[#This Row],[Prima por Contrato]] -> 185142.86
A13: Plantilla | B13: Jugador | C13: Alfons | D13: Luna Biddle | E13: 28000 | F13: =Tabla54[[#This Row],[Salario/mes]]*12 -> 336000 | G13: =(Tabla54[[#This Row],[Salario Total]]/7)/5 -> 9600 | H13: =Tabla54[[#This Row],[Salario Total]]+Tabla54[[#This Row],[Prima por Contrato]] -> 345600
A14: Plantilla | B14: Jugador | C14: Jorge | D14: Montesinos Fernández | E14: 43000 | F14: =Tabla54[[#This Row],[Salario/mes]]*12 -> 516000 | G14: =(Tabla54[[#This Row],[Salario Total]]/7)/5 -> 14742.857 | H14: =Tabla54[[#This Row],[Salario Total]]+Tabla54[[#This Row],[Prima por Contrato]] -> 530742.86
A15: Plantilla | B15: Jugador | C15: Michel | D15: Jordan De Santa | E15: 25000 | F15: =Tabla54[[#This Row],[Salario/mes]]*12 -> 300000 | G15: =(Tabla54[[#This Row],[Salario Total]]/7)/5 -> 8571.4286 | H15: =Tabla54[[#This Row],[Salario Total]]+Tabla54[[#This Row],[Prima por Contrato]] -> 308571.43
... A22: Logística | B22: Directora Club de Fans | C22: Sofía | D22: Todorova | E22: 35000 | F22: =Tabla54[[#This Row],[Salario/mes]]*12 -> 420000 | G22: =(Tabla54[[#This Row],[Salario Total]]/7)/5 -> 12000 | H22: =Tabla54[[#This Row],[Salario Total]]+Tabla54[[#This Row],[Prima por Contrato]] -> 432000
H23: =SUM(H4:H22) -> 13206857

Sheet Balance total
C2: Propietario del club; Darío Nieto Lorente.
C5: Ingresos Totales | E5: Gastos totales
C6: =SUM(Tabla11[Ingresos netos]) -> 1.1337633e+08 | E6: =SUM(' Gancias y Gastos'!C39:H39)+Salarios!H23 -> 38421042
C8: Ganancias Brutas | E8: Ganancias Netas depúes de 25% de impuesto sobre beneficios
C9: =C6-E6 -> 74955284 | E9: =C9-(C9*0.25) -> 56216463
C13: CONCEPTO | D13: CANTIDAD
C14: =C5 -> Ingresos Totales | D14: =C6 -> 1.1337633e+08
C15: =C8 -> Ganancias Brutas | D15: =C9 -> 74955284
C16: =E5 -> Gastos totales | D16: =E6 -> 38421042
C17: =E8 -> Ganancias Netas depúes de 25% de impuesto sobre beneficios | D17: =E9 -> 56216463
